opkit/__init__.py
opkit/__main__.py
opkit/ast_hook.py
opkit/ipython_extension.py
opkit/numpy_ops.py
opkit/pandas_ops.py
opkit/runtime_ops.py
opkit/transform.py
opkit-0.1.0.dist-info/licenses/LICENSE
opkit-0.1.0.dist-info/METADATA
opkit-0.1.0.dist-info/WHEEL
opkit-0.1.0.dist-info/top_level.txt
opkit-0.1.0.dist-info/RECORD
