Metadata-Version: 2.4
Name: opkit
Version: 0.1.0
Summary: Effortlessly extend NumPy and pandas with custom operators using Python AST magic — replace verbose code with concise, expressive operations for advanced data workflows.
Author-email: mihaicezar <mihaicezar@users.noreply.github.com>
License-Expression: MIT
Requires-Python: >=3.9
License-File: LICENSE
Requires-Dist: numpy>=1.20
Requires-Dist: pandas>=1.3
Provides-Extra: jupyter
Requires-Dist: ipython>=7.0; extra == "jupyter"
Provides-Extra: dev
Requires-Dist: pytest>=8.3; extra == "dev"
Requires-Dist: black; extra == "dev"
Requires-Dist: mypy; extra == "dev"
Requires-Dist: flake8; extra == "dev"
Requires-Dist: build; extra == "dev"
Provides-Extra: all
Requires-Dist: ipython>=7.0; extra == "all"
Requires-Dist: pytest>=8.3; extra == "all"
Requires-Dist: black; extra == "all"
Requires-Dist: mypy; extra == "all"
Requires-Dist: flake8; extra == "all"
Requires-Dist: build; extra == "all"
Dynamic: license-file
